LICENSE.rst
MANIFEST.in
README.rst
setup.cfg
setup.py
dtool_azure/__init__.py
dtool_azure/storagebroker.py
dtool_azure/utils.py
dtool_azure.egg-info/PKG-INFO
dtool_azure.egg-info/SOURCES.txt
dtool_azure.egg-info/dependency_links.txt
dtool_azure.egg-info/entry_points.txt
dtool_azure.egg-info/requires.txt
dtool_azure.egg-info/top_level.txt