Metadata-Version: 1.1
Name: dtool-azure
Version: 0.7.1
Summary: Add Azure dataset support to dtool
Home-page: https://github.com/jic-dtool/dtool-azure
Author: Matthew Hartley
Author-email: Matthew.Hartley@jic.ac.uk
License: MIT
Download-URL: https://github.com/jic-dtool/dtool-azure/tarball/0.7.1
Platform: UNKNOWN
